{
    "data": [
        {
            "name": "Zekiri",
            "vorname": "John",
            "personalnr": "000044",
            "bereich_fakultaet": "ITAG",
            "urlaubsjahr": 2024,
            "zusatzurlaub_f_schwerbeh": "",
            "gesamturlaub": 30,
            "gleitzeit": true,
            "urlaubsantraege": [
                {
                    "vom": "01.04.2024",
                    "bis": "10.04.2024",
                    "beantragte_tage": 10,
                    "rest_tage": 20,
                    "antragsteller": "Zekiri",
                    "befuerwortet": "Ja",
                    "genehmigt": "Ja"
                },
                {
                    "vom": "01.07.2024",
                    "bis": "10.07.2024",
                    "beantragte_tage": 10,
                    "rest_tage": 10,
                    "antragsteller": "Zekiri",
                    "befuerwortet": "Ja",
                    "genehmigt": "Ja"
                },
                {
                    "vom": "15.10.2024",
                    "bis": "20.10.2024",
                    "beantragte_tage": 5,
                    "rest_tage": 5,
                    "antragsteller": "Zekiri",
                    "befuerwortet": "Ja",
                    "genehmigt": "Ja"
                },
                {
                    "vom": "01.04.2025",
                    "bis": "10.04.2025",
                    "beantragte_tage": 10,
                    "rest_tage": 10,
                    "antragsteller": "Zekiri",
                    "befuerwortet": "Ja",
                    "genehmigt": "Ja"
                }
            ],
            "hinweis": "Der Urlaub soll grundsätzlich im laufenden Kalenderjahr, spätestens jedoch bis zum 30.09. des Folgejahres genommen werden."
        }
    ],
    "total_processing_time_sec": 34.44883632659912
}